[[[1, 7.8689, "l"], [3, 7.8689, "r"], [3, 8.8525, "r"], [1, 9.8361, "l"], [2, 10.3279, "r"], [0, 10.8197, "l"], [4, 11.8033, "r"], [4, 12.7869, "r"], [4, 13.7705, "r"], [2, 14.2623, "l"], [3, 14.7541, "r"], [1, 15.7377, "l"], [3, 15.7377, "r"], [1, 16.7213, "l"], [3, 17.7049, "r"], [2, 18.1967, "l"], [4, 18.6885, "r"], [0, 19.6721, "l"], [3, 20.6557, "r"], [1, 21.1475, "l"], [1, 21.6393, "l"], [3, 21.6393, "r"], [1, 23.6066, "l"], [3, 23.6066, "r"], [1, 24.5902, "l"], [3, 25.5738, "r"], [1, 26.5574, "l"], [4, 27.541, "r"], [0, 28.5246, "l"], [2, 29.5082, "r"], [1, 30.4918, "l"], [1, 31.4754, "l"], [3, 31.4754, "r"], [3, 32.459, "r"], [1, 33.4426, "l"], [3, 34.4262, "r"], [2, 35.4098, "l"], [4, 36.3934, "r"], [0, 37.377, "l"], [2, 39.3443, "r"], [1, 39.8361, "l"], [3, 39.8361, "r"], [1, 40.3279, "l"], [2, 40.8197, "r"], [0, 41.3115, "l"], [4, 41.8033, "r"], [2, 42.2951, "l"], [3, 42.7869, "r"], [1, 43.2787, "l"], [1, 43.7705, "l"], [3, 44.2623, "r"], [3, 44.7541, "r"], [0, 45.2459, "l"], [0, 45.7377, "l"], [4, 46.2295, "r"], [4, 46.7213, "r"], [2, 47.2131, "l"], [1, 47.7049, "l"], [3, 47.7049, "r"], [3, 48.1967, "r"], [2, 48.6885, "l"], [4, 49.1803, "r"], [0, 49.6721, "l"], [2, 50.1639, "r"], [1, 50.6557, "l"], [3, 51.1475, "r"], [3, 51.6393, "r"], [1, 52.1311, "l"], [1, 52.623, "l"], [1, 53.1148, "l"], [3, 53.1148, "r"], [1, 55.082, "l"], [3, 55.082, "r"], [3, 56.0656, "r"], [1, 57.0492, "l"], [3, 58.0328, "r"], [0, 59.0164, "l"], [4, 60.0, "r"], [2, 60.9836, "l"], [3, 61.9672, "r"], [1, 62.9508, "l"], [3, 62.9508, "r"], [1, 63.9344, "l"], [3, 64.918, "r"], [1, 65.9016, "l"], [2, 66.8852, "r"], [0, 67.8689, "l"], [4, 68.8525, "r"], [2, 70.8197, "l"], [1, 71.3115, "l"], [3, 71.3115, "r"], [3, 71.8033, "r"], [2, 72.2951, "l"], [4, 72.7869, "r"], [0, 73.2787, "l"], [2, 73.7705, "r"], [1, 74.2623, "l"], [3, 74.7541, "r"], [3, 75.2459, "r"], [1, 75.7377, "l"], [1, 76.2295, "l"], [4, 76.7213, "r"], [4, 77.2131, "r"], [0, 77.7049, "l"], [0, 78.1967, "l"], [2, 78.6885, "r"], [1, 79.1803, "l"], [3, 79.1803, "r"], [1, 79.6721, "l"], [2, 80.1639, "r"], [0, 80.6557, "l"], [4, 81.1475, "r"], [2, 81.6393, "l"], [3, 82.1311, "r"], [1, 82.623, "l"], [1, 83.1148, "l"], [3, 83.6066, "r"], [3, 84.0984, "r"], [0, 84.5902, "l"], [3, 84.5902, "r"], [2, 85.082, "r"], [1, 85.5738, "l"], [4, 85.5738, "r"], [1, 86.5574, "l"], [3, 86.5574, "r"], [1, 87.541, "l"], [3, 88.5246, "r"], [2, 89.0164, "l"], [4, 89.5082, "r"], [2, 90.0, "l"], [3, 90.4918, "r"], [3, 91.4754, "r"], [0, 92.459, "l"], [2, 92.9508, "r"], [1, 93.4426, "l"], [2, 93.9344, "r"], [0, 94.4262, "l"], [4, 94.4262, "r"], [0, 95.4098, "l"], [4, 96.3934, "r"], [2, 96.8852, "l"], [3, 97.377, "r"], [2, 97.8689, "l"], [4, 98.3607, "r"], [4, 98.8525, "r"], [0, 99.3443, "l"], [0, 99.8361, "l"], [0, 100.3279, "l"], [4, 100.3279, "r"], [0, 100.8197, "l"], [4, 100.8197, "r"], [2, 101.5574, "r"], [2, 101.8033, "r"]], [], {"ssc_file": "/home/maxwshen/PIU-Simfiles-rayden-61-072924/03 - REBIRTH~PREX 3/(2) 718 - Dance With Me/718 - Dance With Me.ssc", "pack": "REBIRTH~PREX 3", "VERSION": "0.81", "TITLE": "Dance With Me", "ARTIST": "BanYa", "GENRE": "ORIGINAL", "CREDIT": "Andamiro", "BANNER": "718_B.png", "BACKGROUND": "718.PNG", "PREVIEWVID": "718_P.mpg", "MUSIC": "718.MP3", "OFFSET": "-0.761000", "SAMPLESTART": "8.592346", "SAMPLELENGTH": "12.000000", "SELECTABLE": "YES", "SONGTYPE": "ARCADE", "SONGCATEGORY": "ORIGINAL", "VOLUME": "96", "TIMESIGNATURES": "0.000000=4=4", "COMBOS": "0.000000=1", "LABELS": "0.000000=Song Start", "LASTSECONDHINT": "104.856000", "STEPSTYPE": "pump-single", "DESCRIPTION": "S4", "DIFFICULTY": "Edit", "METER": "4", "CHARTSTYLE": "ACTIVE", "shortname": "Dance_With_Me_-_BanYa_S4_ARCADE", "Hold ticks": [], "Manual limb annotation": false, "eNPS annotations": [[23.6066, "1.0 nps\nHalf notes\n122bpm"], [29.5082, "1.0 nps\nHalf notes\n122bpm"], [39.3443, "2.0 nps\nQuarter notes\n122bpm"], [44.7541, "2.0 nps\nQuarter notes\n122bpm"], [50.1639, "2.0 nps\nQuarter notes\n122bpm"], [55.082, "1.0 nps\nHalf notes\n122bpm"], [60.9836, "1.0 nps\nHalf notes\n122bpm"], [70.8197, "2.0 nps\nQuarter notes\n122bpm"], [76.2295, "2.0 nps\nQuarter notes\n122bpm"], [81.6393, "2.0 nps\nQuarter notes\n122bpm"], [88.5246, "2.0 nps\nQuarter notes\n122bpm"], [96.3934, "2.0 nps\nQuarter notes\n122bpm"]], "Segments": [[7.868852459016394, 17.70491803278688, 0, 12], [17.70491803278688, 43.27868852459013, 12, 42], [43.27868852459013, 57.04918032786875, 42, 65], [57.04918032786875, 74.75409836065555, 65, 86], [74.75409836065555, 84.59016393442599, 86, 106], [84.59016393442599, 101.8032786885243, 106, 134]], "Segment metadata": [{"eNPS": 1.3, "level": 3.98, "rare skills": [], "Closest sections": [["You_again_my_love_-_CYO_Style__Henohenomoheji_S3_ARCADE", 0], ["Follow_me_-_SHK_S4_ARCADE", 1], ["Anguished_Unmaking_-_void_S3_ARCADE", 2], ["K.O.A__Alice_In_Wonderworld-_-_Banya_Production_S3_ARCADE", 2], ["Alone_-_HIGHLIGHT_S3_ARCADE", 4]], "Skill badges": ["doublestep", "jump", "jack"]}, {"eNPS": 1.2, "level": 3.87, "rare skills": [], "Closest sections": [["Kitty_Cat_-_Coconut_S3_ARCADE", 4], ["Poseidon_-_Quree_S3_ARCADE", 5], ["Perpetual_-_Qu-ail_S4_ARCADE", 4], ["Wedding_Crashers_-_SHORT_CUT_-_-_SHK_S4_SHORTCUT", 1], ["Selfishness_-_SID-SOUND_S3_ARCADE", 5]], "Skill badges": ["doublestep", "jump"]}, {"eNPS": 1.7, "level": 4.21, "rare skills": [], "Closest sections": [["You_Got_Me_Crazy_-_MAX_S4_ARCADE", 2], ["Highway_Chaser_-_Cosmograph_S4_ARCADE", 3], ["Hestia_-_Gentle_Stick_S4_ARCADE", 6], ["Moonlight_-_BanYa_S4_ARCADE", 6], ["Lala_-_Yassi_Pressman_S3_ARCADE", 2]], "Skill badges": ["jack", "doublestep", "jump"]}, {"eNPS": 1.2, "level": 4.08, "rare skills": [], "Closest sections": [["Selfishness_-_SID-SOUND_S3_ARCADE", 5], ["HTTP_-_Quree_S4_ARCADE", 4], ["Night_Duty_-_A.V._S3_ARCADE", 2], ["Perpetual_-_Qu-ail_S4_ARCADE", 4], ["Wedding_Crashers_-_SHORT_CUT_-_-_SHK_S4_SHORTCUT", 1]], "Skill badges": ["doublestep", "jump"]}, {"eNPS": 2.1, "level": 4.21, "rare skills": [], "Closest sections": [["Hestia_-_Gentle_Stick_S4_ARCADE", 6], ["You_Got_Me_Crazy_-_MAX_S4_ARCADE", 2], ["Rolling_Christmas_-_BanYa_S3_ARCADE", 1], ["Allegro_Piu_Mosso_-_DM_Ashura_S4_ARCADE", 1], ["Pumping_Jumping_-_Banya_Production_S4_ARCADE", 2]], "Skill badges": ["jack", "doublestep", "jump"]}, {"eNPS": 1.7, "level": 4.09, "rare skills": [], "Closest sections": [["Highway_Chaser_-_Cosmograph_S4_ARCADE", 0], ["Idealized_Romance_-_void_S4_ARCADE", 3], ["Nemesis_-_M2U_S4_ARCADE", 3], ["B2_-_MAX_S4_ARCADE", 1], ["Simon_Says,_EURODANCE!!_(feat._SaraM)_-_JehezukielKAZEMURAHideky_S4_ARCADE", 0]], "Skill badges": ["jump", "doublestep", "jack"]}], "eNPS timeline data": [0.0, 0.0, 0.0, 0.0, 0.0, 0.0, 0.0, 0.33, 1.02, 1.02, 2.03, 1.02, 1.02, 1.02, 2.03, 1.02, 1.02, 1.02, 2.03, 1.02, 1.02, 2.03, 0.0, 0.51, 1.02, 1.02, 1.02, 1.02, 1.02, 1.02, 1.02, 1.02, 1.02, 1.02, 1.02, 1.02, 1.02, 1.02, 0.0, 0.81, 2.03, 2.03, 2.03, 2.03, 2.03, 2.03, 2.03, 2.03, 2.03, 2.03, 2.03, 2.03, 2.03, 1.0, 0.0, 0.51, 1.02, 1.02, 1.02, 1.02, 1.02, 1.02, 1.02, 1.02, 1.02, 1.02, 1.02, 1.02, 1.02, 0.0, 0.51, 2.03, 2.03, 2.03, 2.03, 2.03, 2.03, 2.03, 2.03, 2.03, 2.03, 2.03, 2.03, 2.03, 2.03, 2.03, 1.02, 1.02, 1.02, 2.03, 1.0, 1.02, 1.36, 2.03, 1.0, 1.02, 1.36, 2.03, 2.03, 2.03, 2.03, 2.03, 0.0], "eNPS ranges of interest": [[40, 54], [71, 87], [97, 102]], "sord_chartlevel": "S4", "chart_skill_summary": ["doublestep", "jump", "sustained"], "Similar charts": {"2": ["HTTP_-_Quree_S2_ARCADE"], "3": ["Canon_D_-_BanYa_S3_ARCADE", "Amai_Yuuwaku_Dangerous_-_Bakusute_Sotokanda_Icchome_S3_ARCADE", "Move_That_Body_-_DM_Ashura_feat._Skizzo__Hanna_S3_ARCADE"], "4": ["Tantanmen_-_Memme_S4_ARCADE", "Nxde_-_(G)I-DLE_S4_ARCADE", "Cutie_Song_-_Memme_S4_ARCADE"], "5": ["The_Reverie_-_uma_S5_ARCADE", "Overblow2_-_MAX_S5_ARCADE", "Bullfightings_Song_-_Banya_Production_S5_ARCADE"], "6": ["Soldiers_(TANO*C_W_TEAM_RED_ANTHEM)_-_DJ_Noriken_S6_ARCADE", "After_LIKE_-_IVE_S6_ARCADE", "Transacaglia_in_G-minor_-_ATAS_S6_ARCADE"]}, "nps_summary": 2.0, "notetype_bpm_summary": "Quarter notes @ 122 bpm"}]